deltaver/__init__.py
deltaver/__main__.py
deltaver/config.py
deltaver/entry.py
deltaver/parsed_requirements.py
deltaver/version_delta.py
deltaver-0.2.3.dist-info/LICENSE
deltaver-0.2.3.dist-info/METADATA
deltaver-0.2.3.dist-info/WHEEL
deltaver-0.2.3.dist-info/entry_points.txt
deltaver-0.2.3.dist-info/RECORD
