Metadata-Version: 2.1
Name: deltaver
Version: 0.2.3
Summary: 
Author: Almaz Ilaletdinov
Author-email: a.ilaletdinov@yandex.ru
Requires-Python: >=3.9,<4.0
Classifier: Programming Language :: Python :: 3
Classifier: Programming Language :: Python :: 3.9
Classifier: Programming Language :: Python :: 3.10
Classifier: Programming Language :: Python :: 3.11
Classifier: Programming Language :: Python :: 3.12
Requires-Dist: attrs (>=23.0)
Requires-Dist: httpx (>=0,<1)
Requires-Dist: packaging (>=23,<25)
Requires-Dist: rich (>=13.0,<14.0)
Requires-Dist: toml (>=0.10.2,<0.11.0)
Requires-Dist: typer (>=0,<1)
Requires-Dist: typing-extensions (>=4.9,<5.0)
